odoo/addons/partner_identification/README.rst
odoo/addons/partner_identification/__init__.py
odoo/addons/partner_identification/__manifest__.py
odoo/addons/partner_identification/i18n/am.po
odoo/addons/partner_identification/i18n/ar.po
odoo/addons/partner_identification/i18n/bg.po
odoo/addons/partner_identification/i18n/bs.po
odoo/addons/partner_identification/i18n/ca.po
odoo/addons/partner_identification/i18n/cs.po
odoo/addons/partner_identification/i18n/da.po
odoo/addons/partner_identification/i18n/de.po
odoo/addons/partner_identification/i18n/el_GR.po
odoo/addons/partner_identification/i18n/en_GB.po
odoo/addons/partner_identification/i18n/es.po
odoo/addons/partner_identification/i18n/es_AR.po
odoo/addons/partner_identification/i18n/es_CL.po
odoo/addons/partner_identification/i18n/es_CO.po
odoo/addons/partner_identification/i18n/es_CR.po
odoo/addons/partner_identification/i18n/es_DO.po
odoo/addons/partner_identification/i18n/es_EC.po
odoo/addons/partner_identification/i18n/es_ES.po
odoo/addons/partner_identification/i18n/es_MX.po
odoo/addons/partner_identification/i18n/es_PE.po
odoo/addons/partner_identification/i18n/es_PY.po
odoo/addons/partner_identification/i18n/es_VE.po
odoo/addons/partner_identification/i18n/et.po
odoo/addons/partner_identification/i18n/eu.po
odoo/addons/partner_identification/i18n/fa.po
odoo/addons/partner_identification/i18n/fi.po
odoo/addons/partner_identification/i18n/fr.po
odoo/addons/partner_identification/i18n/fr_CA.po
odoo/addons/partner_identification/i18n/fr_CH.po
odoo/addons/partner_identification/i18n/gl.po
odoo/addons/partner_identification/i18n/gl_ES.po
odoo/addons/partner_identification/i18n/he.po
odoo/addons/partner_identification/i18n/hr.po
odoo/addons/partner_identification/i18n/hr_HR.po
odoo/addons/partner_identification/i18n/hu.po
odoo/addons/partner_identification/i18n/id.po
odoo/addons/partner_identification/i18n/it.po
odoo/addons/partner_identification/i18n/ja.po
odoo/addons/partner_identification/i18n/ko.po
odoo13_addon_partner_identification-13.0.1.2.0.dist-info/METADATA
odoo13_addon_partner_identification-13.0.1.2.0.dist-info/WHEEL
odoo13_addon_partner_identification-13.0.1.2.0.dist-info/top_level.txt
odoo13_addon_partner_identification-13.0.1.2.0.dist-info/RECORD
