Metadata-Version: 2.1
Name: odoo13-addon-partner-identification
Version: 13.0.1.2.0
Summary: Partner Identification Numbers
Home-page: https://github.com/OCA/partner-contact
Author: ChriCar Beteiligungs- und Beratungs- GmbH,Tecnativa,Camptocamp,ACSONE SA/NV,LasLabs,Onestein,Odoo Community Association (OCA)
Author-email: support@odoo-community.org
License: AGPL-3
Platform: UNKNOWN
Classifier: Programming Language :: Python
Classifier: Framework :: Odoo
Classifier: License :: OSI Approved :: GNU Affero General Public License v3
Classifier: Development Status :: 5 - Production/Stable
Requires-Python: >=3.5
Requires-Dist: odoo (<13.1dev,>=13.0a)
